README
color.py
pdf.py
setup.py
spiderboy.py
spinslash.py
SpiderBOY.egg-info/PKG-INFO
SpiderBOY.egg-info/SOURCES.txt
SpiderBOY.egg-info/dependency_links.txt
SpiderBOY.egg-info/requires.txt
SpiderBOY.egg-info/top_level.txt