Metadata-Version: 1.1
Name: SpiderBOY
Version: 1.0.0
Summary: A tipical crawler, returns a list of urls
Home-page: http://code.sidelab.es/projects/diegopardilla/wiki
Author: Diego Pardilla
Author-email: diegopardilla@gmail.com
License: GPL v3
Download-URL: git://gitorious.org/practicas_mswl/practicas_mswl_dt.git
Keywords: crawler,spider
Platform: UNKNOWN
